yubikey_paste.py
yubikey_paste-0.2.0.dist-info/METADATA
yubikey_paste-0.2.0.dist-info/WHEEL
yubikey_paste-0.2.0.dist-info/entry_points.txt
yubikey_paste-0.2.0.dist-info/RECORD
